mongodb_odm/__init__.py
mongodb_odm/connection.py
mongodb_odm/data_conversion.py
mongodb_odm/exceptions.py
mongodb_odm/fields.py
mongodb_odm/models.py
mongodb_odm/py.typed
mongodb_odm/types.py
mongodb_odm/utils/__init__.py
mongodb_odm/utils/_internal_models.py
mongodb_odm/utils/apply_indexes.py
mongodb_odm/utils/utils.py
mongodb_odm/utils/validation.py
mongodb_odm-1.2.0.dist-info/WHEEL
mongodb_odm-1.2.0.dist-info/METADATA
mongodb_odm-1.2.0.dist-info/RECORD
