Metadata-Version: 2.3
Name: mongodb-odm
Version: 1.2.0
Summary: MongoDB-ODM, NOSQL databases in Python, designed for simplicity, compatibility, and robustness.
Author: Nayan Biswas
Author-email: Nayan Biswas <nayan32biswas@gmail.com>
Classifier: Development Status :: 4 - Beta
Classifier: Operating System :: OS Independent
Classifier: Intended Audience :: Developers
Classifier: Intended Audience :: Science/Research
Classifier: Intended Audience :: System Administrators
Classifier: License :: OSI Approved :: MIT License
Classifier: Programming Language :: Python :: 3 :: Only
Classifier: Programming Language :: Python :: 3.9
Classifier: Programming Language :: Python :: 3.10
Classifier: Programming Language :: Python :: 3.11
Classifier: Programming Language :: Python :: 3.12
Classifier: Programming Language :: Python :: 3.13
Classifier: Programming Language :: Python :: 3.14
Classifier: Topic :: Database
Classifier: Topic :: Database :: Database Engines/Servers
Classifier: Topic :: Internet
Classifier: Topic :: Internet :: WWW/HTTP :: HTTP Servers
Classifier: Topic :: Internet :: WWW/HTTP
Classifier: Typing :: Typed
Requires-Dist: pydantic>=2.11.0
Requires-Dist: pymongo>=4.13.0
Requires-Dist: black>=25.1.0 ; extra == 'dev'
Requires-Dist: coverage[toml]>=7.10.0 ; extra == 'dev'
Requires-Dist: pytest>=8.4.0 ; extra == 'dev'
Requires-Dist: pytest-asyncio>=1.1.0 ; extra == 'dev'
Requires-Dist: mypy==1.17.1 ; extra == 'dev'
Requires-Dist: pre-commit>=3.3.3 ; extra == 'dev'
Requires-Dist: ruff>=0.12.8 ; extra == 'dev'
Requires-Dist: mkdocs>=1.6.1 ; extra == 'docs'
Requires-Dist: mkdocstrings[python]~=0.30.1 ; extra == 'docs'
Requires-Dist: markdown-include ; extra == 'docs'
Requires-Dist: mkdocs-material>=9.7.0 ; extra == 'docs'
Requires-Dist: mdx-include ; extra == 'docs'
Requires-Dist: pyyaml>=6.0.3 ; extra == 'docs'
Requires-Python: >=3.9, <4.0
Project-URL: Changelog, https://mongodb-odm.readthedocs.io/en/latest/release-notes/
Project-URL: Documentation, https://mongodb-odm.readthedocs.io
Project-URL: Homepage, https://github.com/nayan32biswas/mongodb-odm
Project-URL: Issues, https://github.com/nayan32biswas/mongodb-odm/issues
Project-URL: Repository, https://github.com/nayan32biswas/mongodb-odm
Provides-Extra: dev
Provides-Extra: docs
